zensols/dsprov/__init__.py
zensols/dsprov/app.py
zensols/dsprov/cli.py
zensols/dsprov/domain.py
zensols/dsprov/stash.py
zensols/dsprov/resources/app.conf
zensols/dsprov/resources/default.conf
zensols/dsprov/resources/obj.yml
zensols.dsprov-0.0.1.dist-info/METADATA
zensols.dsprov-0.0.1.dist-info/WHEEL
zensols.dsprov-0.0.1.dist-info/entry_points.txt
zensols.dsprov-0.0.1.dist-info/top_level.txt
zensols.dsprov-0.0.1.dist-info/RECORD
