Metadata-Version: 2.1
Name: zensols.dsprov
Version: 0.0.1
Summary: This library provides integrated MIMIC-III with discharge summary provenance of data annotations and Pythonic classes.
Home-page: https://github.com/plandes/dsprov
Download-URL: https://github.com/plandes/dsprov/releases/download/v0.0.1/zensols.dsprov-0.0.1-py3-none-any.whl
Author: Paul Landes
Author-email: landes@mailc.net
Keywords: tooling
Requires-Dist: zensols.mimicsid (~=1.3.1)
